aviation_stack_sdk-1.0.0.dist-info/licenses/LICENSE
aviationstack/__init__.py
aviationstack/api_helper.py
aviationstack/aviationstack_client.py
aviationstack/configuration.py
aviationstack/controllers/__init__.py
aviationstack/controllers/aircraft_types_controller.py
aviationstack/controllers/airlines_controller.py
aviationstack/controllers/airplanes_controller.py
aviationstack/controllers/airports_controller.py
aviationstack/controllers/base_controller.py
aviationstack/controllers/cities_controller.py
aviationstack/controllers/countries_controller.py
aviationstack/controllers/flight_future_schedules_controller.py
aviationstack/controllers/flight_schedules_controller.py
aviationstack/controllers/flights_controller.py
aviationstack/controllers/routes_controller.py
aviationstack/controllers/taxes_controller.py
aviationstack/exceptions/__init__.py
aviationstack/exceptions/api_exception.py
aviationstack/http/__init__.py
aviationstack/http/http_call_back.py
aviationstack/http/http_method_enum.py
aviationstack/http/http_request.py
aviationstack/http/http_response.py
aviationstack/http/auth/__init__.py
aviationstack/http/auth/custom_query_authentication.py
aviationstack/models/__init__.py
aviationstack/models/aircraft.py
aviationstack/models/aircraft_1.py
aviationstack/models/aircraft_4.py
aviationstack/models/airline.py
aviationstack/models/airline_2.py
aviationstack/models/airline_4.py
aviationstack/models/airline_6.py
aviationstack/models/arrival.py
aviationstack/models/arrival_2.py
aviationstack/models/arrival_4.py
aviationstack/models/arrival_6.py
aviationstack/models/arrival_8.py
aviationstack/models/codeshared.py
aviationstack/models/codeshared_1.py
aviationstack/models/codeshared_6.py
aviationstack/models/codeshared_61.py
aviationstack/models/datum.py
aviationstack/models/datum_10.py
aviationstack/models/datum_12.py
aviationstack/models/datum_14.py
aviationstack/models/datum_16.py
aviationstack/models/datum_18.py
aviationstack/models/datum_2.py
aviationstack/models/datum_20.py
aviationstack/models/datum_22.py
aviation_stack_sdk-1.0.0.dist-info/METADATA
aviation_stack_sdk-1.0.0.dist-info/WHEEL
aviation_stack_sdk-1.0.0.dist-info/top_level.txt
aviation_stack_sdk-1.0.0.dist-info/RECORD
