Metadata-Version: 2.4
Name: aviation-stack-sdk
Version: 1.0.0
Summary: AviationStack API: A comprehensive aviation data API that provides real-time flight tracking, status information, and access to aviation databases including flights, routes, airports, airlines, aircraft types, and schedules. It enables developers to retrieve live flight data and comprehensive aviation information through RESTful endpoints.
Author-email: Muhammad Hamza Shahzad <muhammad.hamza@apimatic.io>
Project-URL: Documentation, https://docs.apimatic.io/
Requires-Python: >=3.7
License-File: LICENSE
Requires-Dist: apimatic-core>=0.2.20,~=0.2.0
Requires-Dist: apimatic-core-interfaces>=0.1.5,~=0.1.0
Requires-Dist: apimatic-requests-client-adapter>=0.1.6,~=0.1.0
Provides-Extra: testutils
Requires-Dist: pytest>=7.2.2; extra == "testutils"
Dynamic: license-file
